docs/Makefile
docs/__init__.py
docs/make.bat
examples/__init__.py
examples/cny_exchange_rate.py
examples/books_to_scrape/__init__.py
examples/books_to_scrape/manager.py
examples/books_to_scrape/scraper.py
examples/books_to_scrape/settings.py
examples/books_to_scrape/workgroup.py
examples/books_to_scrape/persistence/__init__.py
examples/books_to_scrape/persistence/newt_db.py
examples/books_to_scrape/persistence/serialization.py
examples/books_to_scrape/schedulers/__init__.py
examples/books_to_scrape/schedulers/brokers/__init__.py
examples/books_to_scrape/schedulers/brokers/client_main.py
examples/books_to_scrape/schedulers/brokers/worker_main.py
examples/books_to_scrape/schedulers/stateful_book/__init__.py
examples/books_to_scrape/schedulers/stateful_book/main.py
tests/books_toscrape/__init__.py
tests/books_toscrape/book_titles.xlsx
tests/books_toscrape/books_toscrape_index.html
tests/books_toscrape/test_books_toscrape.py
tests/unit/__init__.py
tests/unit/test_internal.py
tests/unit/books/__init__.py
tests/unit/browsers/__init__.py
tests/unit/browsers/test_splash_browser.py
tests/unit/managers/__init__.py
tests/unit/persistence/__init__.py
tests/unit/persistence/test_exporters.py
tests/unit/persistence/test_item.py
tests/unit/scrapers/__init__.py
tests/unit/utility/__init__.py
tests/unit/utility/test_utility_serialize.py
tests/unit/workers/__init__.py
transistor/__init__.py
transistor/__version__.py
transistor/_internal.py
transistor/exceptions.py
transistor/headers.py
transistor/browsers/__init__.py
transistor/browsers/mixin.py
transistor/browsers/splash_browser.py
transistor/crawlers/__init__.py
transistor/crawlers/splash_crawler_abc.py
transistor/managers/__init__.py
transistor/managers/base_manager.py
transistor/persistence/__init__.py
transistor/persistence/containers.py
transistor/persistence/item.py
transistor/persistence/loader.py
transistor/persistence/exporters/__init__.py
transistor/persistence/exporters/base.py
transistor-0.2.4.dist-info/AUTHORS
transistor-0.2.4.dist-info/LICENSE
transistor-0.2.4.dist-info/METADATA
transistor-0.2.4.dist-info/WHEEL
transistor-0.2.4.dist-info/top_level.txt
transistor-0.2.4.dist-info/RECORD
