Metadata-Version: 2.1
Name: transistor
Version: 0.2.4
Summary: A web scraping framework for intelligent use cases.
Home-page: https://github.com/bomquote/transistor
Author: Bob Jordan
Author-email: bmjjr@bomquote.com
License: MIT
Download-URL: https://github.com/bomquote/transistor/archive/v0.2.4.tar.gz
Keywords: scraping,crawling,spiders,requests,beautifulsoup4,mechanicalsoup,framework,headless-browser
Platform: UNKNOWN
Classifier: License :: OSI Approved :: MIT License
Classifier: Programming Language :: Python
Classifier: Programming Language :: Python :: 3
Classifier: Programming Language :: Python :: 3.6
Classifier: Programming Language :: Python :: 3.7
Classifier: Programming Language :: Python :: Implementation :: CPython
Classifier: Programming Language :: Python :: Implementation :: PyPy
Requires-Python: >=3.6.0
Requires-Dist: mechanicalsoup (<0.13.0,>=0.11.0)
Requires-Dist: requests (<3.0,>=2.20.1)
Requires-Dist: urllib3 (<2.0,>=1.24.1)
Requires-Dist: keyring (<22.0,>=17.0.0)
Requires-Dist: kombu (>=4.2.1)
Requires-Dist: lxml (<5.0,>=4.2.5)
Requires-Dist: lz4 (<4.0,>=2.1.2)
Requires-Dist: openpyxl (<4.0,>=2.5.0)
Requires-Dist: pyexcel (<0.7.0,>=0.5.15)
Requires-Dist: pyexcel-io (<0.6.0,>=0.5.19)
Requires-Dist: pyexcel-ods3 (<0.6.0,>=0.5.3)
Requires-Dist: pyexcel-webio (<0.2.0,>=0.1.4)
Requires-Dist: pyexcel-xls (<0.6.0,>=0.5.8)
Requires-Dist: pyexcel-xlsx (<0.6.0,>=0.5.7)
Requires-Dist: cookiecutter (<2.0,>=1.6.0)
Requires-Dist: cssselect (<2.0,>=1.0.3)
Requires-Dist: w3lib (<2.0,>=1.19.0)
Requires-Dist: pycryptodome (<4.0,>=3.7.2)
Requires-Dist: gevent (<21.0,>=1.3.7)
Provides-Extra: newt.db
Requires-Dist: RelStorage[postgresql] (==2.1.1) ; extra == 'newt.db'
Requires-Dist: newt.db (>=0.9.0) ; extra == 'newt.db'
Requires-Dist: zodbpickle (>=1.0.2) ; extra == 'newt.db'
Requires-Dist: persistent (>=4.4.3) ; extra == 'newt.db'
Requires-Dist: zodb (>=5.5.1) ; extra == 'newt.db'
Provides-Extra: redis
Requires-Dist: redis (>=3.0.1) ; extra == 'redis'
